amadeus/__init__.py
amadeus/amadeus.py
amadeus/version.py
amadeus/airport/__init__.py
amadeus/airport/_predictions.py
amadeus/airport/predictions/__init__.py
amadeus/airport/predictions/_on_time.py
amadeus/analytics/__init__.py
amadeus/analytics/_itinerary_price_metrics.py
amadeus/booking/__init__.py
amadeus/booking/_flight_order.py
amadeus/booking/_flight_orders.py
amadeus/booking/_hotel_bookings.py
amadeus/client/__init__.py
amadeus/client/access_token.py
amadeus/client/decorator.py
amadeus/client/direction.py
amadeus/client/errors.py
amadeus/client/location.py
amadeus/client/request.py
amadeus/client/response.py
amadeus/e_reputation/__init__.py
amadeus/e_reputation/_hotel_sentiments.py
amadeus/media/__init__.py
amadeus/media/_files.py
amadeus/media/files/__init__.py
amadeus/media/files/_generated_photos.py
amadeus/mixins/__init__.py
amadeus/mixins/encoder.py
amadeus/mixins/http.py
amadeus/mixins/pagination.py
amadeus/mixins/parser.py
amadeus/mixins/validator.py
amadeus/namespaces/__init__.py
amadeus/namespaces/_airport.py
amadeus/namespaces/_analytics.py
amadeus/namespaces/_booking.py
amadeus/namespaces/_e_reputation.py
amadeus/namespaces/_media.py
amadeus/namespaces/_reference_data.py
amadeus/namespaces/_safety.py
amadeus/namespaces/_schedule.py
amadeus/namespaces/_shopping.py
amadeus/namespaces/_travel.py
amadeus/namespaces/core.py
amadeus/reference_data/__init__.py
amadeus/reference_data/_airlines.py
amadeus/reference_data/_location.py
amadeus/reference_data/_locations.py
amadeus/reference_data/_recommended_locations.py
amadeus/reference_data/_urls.py
amadeus/reference_data/locations/__init__.py
amadeus/reference_data/locations/_airports.py
amadeus/reference_data/locations/_point_of_interest.py
amadeus/reference_data/locations/_points_of_interest.py
amadeus/reference_data/locations/points_of_interest/__init__.py
amadeus/reference_data/locations/points_of_interest/_by_square.py
amadeus/reference_data/urls/__init__.py
amadeus-5.1.0.dist-info/LICENSE
amadeus-5.1.0.dist-info/METADATA
amadeus-5.1.0.dist-info/WHEEL
amadeus-5.1.0.dist-info/top_level.txt
amadeus-5.1.0.dist-info/RECORD
