Metadata-Version: 2.1
Name: amadeus
Version: 5.1.0
Summary: Python module for the Amadeus travel APIs
Home-page: https://github.com/amadeus4dev/amadeus-python
Author: Amadeus
Author-email: developers@amadeus.com
License: MIT
Platform: UNKNOWN
Classifier: License :: OSI Approved :: MIT License
Classifier: Operating System :: OS Independent
Classifier: Programming Language :: Python
Classifier: Programming Language :: Python :: 3.4
Classifier: Programming Language :: Python :: 3.5
Classifier: Programming Language :: Python :: 3.6
Classifier: Topic :: Software Development :: Libraries :: Python Modules
Requires-Python: >=3.4.8
